automation_tools/__init__.py
automation_tools/excel_to_csv_converter.py
automation_tools-1.0.8.dist-info/LICENSE
automation_tools-1.0.8.dist-info/METADATA
automation_tools-1.0.8.dist-info/WHEEL
automation_tools-1.0.8.dist-info/top_level.txt
automation_tools-1.0.8.dist-info/RECORD
