Metadata-Version: 2.1
Name: automation-tools
Version: 1.0.8
Summary: A suite of automation tools for various tasks.
Home-page: https://github.com/sportyomar/automation_tools
Author: Omar Lydale Morrison
Author-email: omar.morrison@sportyventures.com
License: MIT
License-File: LICENSE
Requires-Dist: openpyxl
